aiopypes/__init__.py
aiopypes/app.py
aiopypes/balance.py
aiopypes/exception.py
aiopypes/graph.py
aiopypes/pipeline.py
aiopypes/scale.py
aiopypes/signal.py
aiopypes/stream.py
aiopypes/task.py
aiopypes-1.1.0.dist-info/LICENSE
aiopypes-1.1.0.dist-info/METADATA
aiopypes-1.1.0.dist-info/WHEEL
aiopypes-1.1.0.dist-info/entry_points.txt
aiopypes-1.1.0.dist-info/top_level.txt
aiopypes-1.1.0.dist-info/RECORD
