Metadata-Version: 2.1
Name: aiopypes
Version: 1.1.0
Summary: Scalable async pipelines in Python, made easy
Author-email: mroumanos <mroumanos@pm.me>
License: MIT License
Project-URL: Homepage, https://github.com/mroumanos/aiopypes
Project-URL: Documentation, https://aiopypes.readthedocs.io
Project-URL: Repository, https://github.com/mroumanos/aiopypes.git
Keywords: asyncio,pipeline,pipe,stream
Classifier: Intended Audience :: Developers
Classifier: License :: OSI Approved :: MIT License
Classifier: Programming Language :: Python
Classifier: Programming Language :: Python :: 3
Classifier: Programming Language :: Python :: 3.10
Classifier: Programming Language :: Python :: 3.11
Classifier: Programming Language :: Python :: 3.12
Classifier: Operating System :: OS Independent
Requires-Python: >=3.10
License-File: LICENSE
Requires-Dist: tomli ; python_version >= "3.10"
Provides-Extra: dev
Requires-Dist: black ; extra == 'dev'
Requires-Dist: bumpver ; extra == 'dev'
Requires-Dist: isort ; extra == 'dev'
Requires-Dist: pip-tools ; extra == 'dev'
Requires-Dist: pytest ; extra == 'dev'
